[
  {
    "code" : "15",
    "name" : "Arica y Parinacota",
    "children" : [
      {
        "name" : "Arica",
        "code" : "151",
        "children" : [
          {
            "code" : "15101",
            "name" : "Arica",
            "latitude" : -18.475,
            "longitude" : -70.3144444
          },
          {
            "code" : "15102",
            "name" : "Camarones",
            "latitude" : -19.0166667,
            "longitude" : -69.8666667
          }
        ]
      },
      {
        "name" : "Parinacota",
        "code" : "152",
        "children" : [
          {
            "code" : "15201",
            "name" : "Putre",
            "latitude" : -18.1916667,
            "longitude" : -69.5977778
          },
          {
            "code" : "15202",
            "name" : "General Lagos",
            "latitude" : -17.5666667,
            "longitude" : -69.5
          }
        ]
      }
    ]
  },
  {
    "code" : "01",
    "name" : "Tarapacá",
    "children" : [
      {
        "name" : "Iquique",
        "code" : "011",
        "children" : [
          {
            "code" : "1101",
            "name" : "Iquique",
            "latitude" : -20.2166667,
            "longitude" : -70.1666667
          },
          {
            "code" : "1102",
            "name" : "Alto Hospicio",
            "latitude" : -20.25,
            "longitude" : -70.1166667
          }
        ]
      },
      {
        "name" : "Tamarugal",
        "code" : "014",
        "children" : [
          {
            "code" : "1201",
            "name" : "Pozo Almonte",
            "latitude" : -20.2666667,
            "longitude" : -69.7833333
          },
          {
            "code" : "1402",
            "name" : "Camiña",
            "latitude" : -19.3,
            "longitude" : -69.4166667
          },
          {
            "code" : "1403",
            "name" : "Colchane",
            "latitude" : -19.2666667,
            "longitude" : -68.6166667
          },
          {
            "code" : "1404",
            "name" : "Huara",
            "latitude" : -19.9666667,
            "longitude" : -69.7666667
          },
          {
            "code" : "1405",
            "name" : "Pica",
            "latitude" : -20.5,
            "longitude" : -69.3333333
          }
        ]
      }
    ]
  },
  {
    "code" : "02",
    "name" : "Antofagasta",
    "children" : [
      {
        "name" : "Antofagasta",
        "code" : "021",
        "children" : [
          {
            "code" : "2101",
            "name" : "Antofagasta",
            "latitude" : -20.5,
            "longitude" : -69.3333333
          },
          {
            "code" : "2102",
            "name" : "Mejillones",
            "latitude" : -23.1,
            "longitude" : -70.45
          },
          {
            "code" : "2103",
            "name" : "Sierra Gorda",
            "latitude" : -22.8833333,
            "longitude" : -69.3166667
          },
          {
            "code" : "2104",
            "name" : "Taltal",
            "latitude" : -25.2833333,
            "longitude" : -69.7666667
          }
        ]
      },
      {
        "name" : "El Loa",
        "code" : "022",
        "children" : [
          {
            "code" : "2201",
            "name" : "Calama",
            "latitude" : -22.4666667,
            "longitude" : -68.9166667
          },
          {
            "code" : "2202",
            "name" : "Ollagüe",
            "latitude" : -22.4666667,
            "longitude" : -68.9166667
          },
          {
            "code" : "2203",
            "name" : "San Pedro de Atacama",
            "latitude" : -22.9166667,
            "longitude" : -68.2166667
          }
        ]
      },
      {
        "name" : "Tocopilla",
        "code" : "023",
        "children" : [
          {
            "code" : "2301",
            "name" : "Tocopilla",
            "latitude" : -22.0666667,
            "longitude" : -70.2
          },
          {
            "code" : "2302",
            "name" : "María Elena",
            "latitude" : -22.35,
            "longitude" : -69.6666667
          }
        ]
      }
    ]
  },
  {
    "code" : "03",
    "name" : "Atacama",
    "children" : [
      {
        "name" : "Copiapó",
        "code" : "031",
        "children" : [
          {
            "code" : "3101",
            "name" : "Copiapó",
            "latitude" : -27.3666667,
            "longitude" : -70.3166667
          },
          {
            "code" : "3102",
            "name" : "Caldera",
            "latitude" : -27.0666667,
            "longitude" : -70.8166667
          },
          {
            "code" : "3103",
            "name" : "Tierra Amarilla",
            "latitude" : -27.4666667,
            "longitude" : -70.2666667
          }
        ]
      },
      {
        "name" : "Chañaral",
        "code" : "032",
        "children" : [
          {
            "code" : "3201",
            "name" : "Chañaral",
            "latitude" : -26.3333333,
            "longitude" : -70.6
          },
          {
            "code" : "3202",
            "name" : "Diego de Almagro",
            "latitude" : -26.3666667,
            "longitude" : -70.05
          }
        ]
      },
      {
        "name" : "Huasco",
        "code" : "033",
        "children" : [
          {
            "code" : "3301",
            "name" : "Vallenar",
            "latitude" : -28.5666667,
            "longitude" : -70.75
          },
          {
            "code" : "3302",
            "name" : "Alto del Carmen",
            "latitude" : -28.9336111,
            "longitude" : -70.4622222
          },
          {
            "code" : "3303",
            "name" : "Freirina",
            "latitude" : -28.5,
            "longitude" : -71.0666667
          },
          {
            "code" : "3304",
            "name" : "Huasco",
            "latitude" : -28.45,
            "longitude" : -71.2166667
          }
        ]
      }
    ]
  },
  {
    "code" : "04",
    "name" : "Coquimbo",
    "children" : [
      {
        "name" : "Elqui",
        "code" : "041",
        "children" : [
          {
            "code" : "4101",
            "name" : "La Serena",
            "latitude" : -29.9,
            "longitude" : -71.25
          },
          {
            "code" : "4102",
            "name" : "Coquimbo",
            "latitude" : -29.95,
            "longitude" : -71.3333333
          },
          {
            "code" : "4103",
            "name" : "Andacollo",
            "latitude" : -30.2166667,
            "longitude" : -71.0833333
          },
          {
            "code" : "4104",
            "name" : "La Higuera",
            "latitude" : -29.5,
            "longitude" : -71.2666667
          },
          {
            "code" : "4105",
            "name" : "Paihuano",
            "latitude" : -30.0166667,
            "longitude" : -70.5166667
          },
          {
            "code" : "4106",
            "name" : "Vicuña",
            "latitude" : -30.0166667,
            "longitude" : -70.7
          }
        ]
      },
      {
        "name" : "Choapa",
        "code" : "042",
        "children" : [
          {
            "code" : "4201",
            "name" : "Illapel",
            "latitude" : -31.6166667,
            "longitude" : -71.15
          },
          {
            "code" : "4202",
            "name" : "Canela",
            "latitude" : -31.4,
            "longitude" : -71.45
          },
          {
            "code" : "4203",
            "name" : "Los Vilos",
            "latitude" : -31.9,
            "longitude" : -71.5166667
          },
          {
            "code" : "4204",
            "name" : "Salamanca",
            "latitude" : -31.7666667,
            "longitude" : -70.9666667
          }
        ]
      },
      {
        "name" : "Limarí",
        "code" : "043",
        "children" : [
          {
            "code" : "4301",
            "name" : "Ovalle",
            "latitude" : -30.5833333,
            "longitude" : -71.2
          },
          {
            "code" : "4302",
            "name" : "Combarbalá",
            "latitude" : -31.1666667,
            "longitude" : -71.05
          },
          {
            "code" : "4303",
            "name" : "Monte Patria",
            "latitude" : -30.6833333,
            "longitude" : -70.9333333
          },
          {
            "code" : "4304",
            "name" : "Punitaqui",
            "latitude" : -30.9,
            "longitude" : -71.2666667
          },
          {
            "code" : "4305",
            "name" : "Río Hurtado",
            "latitude" : -30.2666667,
            "longitude" : -70.7
          }
        ]
      }
    ]
  },
  {
    "code" : "05",
    "name" : "Valparaíso",
    "children" : [
      {
        "name" : "Valparaíso",
        "code" : "051",
        "children" : [
          {
            "code" : "5101",
            "name" : "Valparaíso",
            "latitude" : -33.0458333,
            "longitude" : -71.6163889
          },
          {
            "code" : "5102",
            "name" : "Casablanca",
            "latitude" : -33.3166667,
            "longitude" : -71.4166667
          },
          {
            "code" : "5103",
            "name" : "Concón",
            "latitude" : -32.9166667,
            "longitude" : -71.5166667
          },
          {
            "code" : "5104",
            "name" : "Juan Fernández",
            "latitude" : -33.6166667,
            "longitude" : -78.8666667
          },
          {
            "code" : "5105",
            "name" : "Puchuncaví",
            "latitude" : -32.7333333,
            "longitude" : -71.4166667
          },
          {
            "code" : "5107",
            "name" : "Quintero",
            "latitude" : -32.7833333,
            "longitude" : -71.5333333
          },
          {
            "code" : "5109",
            "name" : "Viña del Mar",
            "latitude" : -33.0333333,
            "longitude" : -71.5333333
          },
          {
            "code" : "5801",
            "name" : "Quilpué",
            "latitude" : -33.05,
            "longitude" : -71.45
          },
          {
            "code" : "5804",
            "name" : "Villa Alemana",
            "latitude" : -33.05,
            "longitude" : -71.3666667
          }
        ]
      },
      {
        "name" : "Isla de Pascua",
        "code" : "052",
        "children" : [
          {
            "code" : "5201",
            "name" : "Isla de Pascua",
            "latitude" : -27.0833333,
            "longitude" : -109.375
          }
        ]
      },
      {
        "name" : "Los Andes",
        "code" : "053",
        "children" : [
          {
            "code" : "5301",
            "name" : "Los Andes",
            "latitude" : -32.8166667,
            "longitude" : -70.6166667
          },
          {
            "code" : "5302",
            "name" : "Calle Larga",
            "latitude" : -32.85,
            "longitude" : -70.6333333
          },
          {
            "code" : "5303",
            "name" : "Rinconada",
            "latitude" : -32.8333333,
            "longitude" : -70.7
          },
          {
            "code" : "5304",
            "name" : "San Esteban",
            "latitude" : -32.8,
            "longitude" : -70.5833333
          }
        ]
      },
      {
        "name" : "Petorca",
        "code" : "054",
        "children" : [
          {
            "code" : "5401",
            "name" : "La Ligua",
            "latitude" : -32.45,
            "longitude" : -71.2166667
          },
          {
            "code" : "5402",
            "name" : "Cabildo",
            "latitude" : -32.4166667,
            "longitude" : -71.1333333
          },
          {
            "code" : "5403",
            "name" : "Papudo",
            "latitude" : -32.5166667,
            "longitude" : -71.45
          },
          {
            "code" : "5404",
            "name" : "Petorca",
            "latitude" : -32.25,
            "longitude" : -70.9333333
          },
          {
            "code" : "5405",
            "name" : "Zapallar",
            "latitude" : -32.5333333,
            "longitude" : -71.4666667
          }
        ]
      },
      {
        "name" : "Quillota",
        "code" : "055",
        "children" : [
          {
            "code" : "5501",
            "name" : "Quillota",
            "latitude" : -32.8833333,
            "longitude" : -71.2666667
          },
          {
            "code" : "5502",
            "name" : "La Calera",
            "latitude" : -32.7833333,
            "longitude" : -71.2166667
          },
          {
            "code" : "5503",
            "name" : "Hijuelas",
            "latitude" : -32.8,
            "longitude" : -71.1666667
          },
          {
            "code" : "5504",
            "name" : "La Cruz",
            "latitude" : -32.8166667,
            "longitude" : -71.2333333
          },
          {
            "code" : "5506",
            "name" : "Nogales",
            "latitude" : -32.7166667,
            "longitude" : -71.2333333
          },
          {
            "code" : "5802",
            "name" : "Limache",
            "latitude" : -32.9833333,
            "longitude" : -71.2833333
          },
          {
            "code" : "5803",
            "name" : "Olmué",
            "latitude" : -33,
            "longitude" : -71.2
          }
        ]
      },
      {
        "name" : "San Antonio",
        "code" : "056",
        "children" : [
          {
            "code" : "5601",
            "name" : "San Antonio",
            "latitude" : -33.6,
            "longitude" : -71.6166667
          },
          {
            "code" : "5602",
            "name" : "Algarrobo",
            "latitude" : -33.3911111,
            "longitude" : -71.6927778
          },
          {
            "code" : "5603",
            "name" : "Cartagena",
            "latitude" : -33.55,
            "longitude" : -71.6
          },
          {
            "code" : "5604",
            "name" : "El Quisco",
            "latitude" : -33.4,
            "longitude" : -71.7
          },
          {
            "code" : "5605",
            "name" : "El Tabo",
            "latitude" : -33.45,
            "longitude" : -71.6666667
          },
          {
            "code" : "5606",
            "name" : "Santo Domingo",
            "latitude" : -33.6333333,
            "longitude" : -71.65
          }
        ]
      },
      {
        "name" : "San Felipe de Aconcagua",
        "code" : "057",
        "children" : [
          {
            "code" : "5701",
            "name" : "San Felipe",
            "latitude" : -32.75,
            "longitude" : -70.7333333
          },
          {
            "code" : "5702",
            "name" : "Catemu",
            "latitude" : -32.6333333,
            "longitude" : -71.0333333
          },
          {
            "code" : "5703",
            "name" : "Llaillay",
            "latitude" : -32.85,
            "longitude" : -70.9666667
          },
          {
            "code" : "5704",
            "name" : "Panquehue",
            "latitude" : -32.8,
            "longitude" : -70.8333333
          },
          {
            "code" : "5705",
            "name" : "Putaendo",
            "latitude" : -32.6333333,
            "longitude" : -70.7333333
          },
          {
            "code" : "5706",
            "name" : "Santa María",
            "latitude" : -32.75,
            "longitude" : -70.6666667
          }
        ]
      }
    ]
  },
  {
    "code" : "06",
    "name" : "O’Higgins",
    "children" : [
      {
        "name" : "Cachapoal",
        "code" : "061",
        "children" : [
          {
            "code" : "6101",
            "name" : "Rancagua",
            "latitude" : -34.1652778,
            "longitude" : -70.7397222
          },
          {
            "code" : "6102",
            "name" : "Codegua",
            "latitude" : -34.0333333,
            "longitude" : -70.6666667
          },
          {
            "code" : "6103",
            "name" : "Coinco",
            "latitude" : -34.2666667,
            "longitude" : -70.9666667
          },
          {
            "code" : "6104",
            "name" : "Coltauco",
            "latitude" : 34.287229,
            "longitude" : -71.085723
          },
          {
            "code" : "6105",
            "name" : "Doñihue",
            "latitude" : -34.2333333,
            "longitude" : -70.9666667
          },
          {
            "code" : "6106",
            "name" : "Graneros",
            "latitude" : -34.0647222,
            "longitude" : -70.7266667
          },
          {
            "code" : "6107",
            "name" : "Las Cabras",
            "latitude" : -34.3,
            "longitude" : -71.3166667
          },
          {
            "code" : "6108",
            "name" : "Machalí",
            "latitude" : -34.1825,
            "longitude" : -70.6511111
          },
          {
            "code" : "6109",
            "name" : "Malloa",
            "latitude" : -34.45,
            "longitude" : -70.95
          },
          {
            "code" : "6110",
            "name" : "Mostazal",
            "latitude" : -33.9833333,
            "longitude" : -70.7
          },
          {
            "code" : "6111",
            "name" : "Olivar",
            "latitude" : -34.21,
            "longitude" : -70.8175
          },
          {
            "code" : "6112",
            "name" : "Peumo",
            "latitude" : -34.4,
            "longitude" : -71.1666667
          },
          {
            "code" : "6113",
            "name" : "Pichidegua",
            "latitude" : -34.35,
            "longitude" : -71.3
          },
          {
            "code" : "6114",
            "name" : "Quinta de Tilcoco",
            "latitude" : -34.35,
            "longitude" : -70.9833333
          },
          {
            "code" : "6115",
            "name" : "Rengo",
            "latitude" : -34.4166667,
            "longitude" : -70.8666667
          },
          {
            "code" : "6116",
            "name" : "Requínoa",
            "latitude" : -34.2833333,
            "longitude" : -70.8333333
          },
          {
            "code" : "6117",
            "name" : "San Vicente",
            "latitude" : -34.5,
            "longitude" : -71.1333333
          }
        ]
      },
      {
        "name" : "Cardenal Caro",
        "code" : "062",
        "children" : [
          {
            "code" : "6201",
            "name" : "Pichilemu",
            "latitude" : -34.3833333,
            "longitude" : -72
          },
          {
            "code" : "6202",
            "name" : "La Estrella",
            "latitude" : -34.2,
            "longitude" : -71.6666667
          },
          {
            "code" : "6203",
            "name" : "Litueche",
            "latitude" : -34.1166667,
            "longitude" : -71.7333333
          },
          {
            "code" : "6204",
            "name" : "Marchigüe",
            "latitude" : -34.4,
            "longitude" : -71.6333333
          },
          {
            "code" : "6205",
            "name" : "Navidad",
            "latitude" : -33.9333333,
            "longitude" : -71.8333333
          },
          {
            "code" : "6206",
            "name" : "Paredones",
            "latitude" : -34.7833333,
            "longitude" : -71.1666667
          }
        ]
      },
      {
        "name" : "Colchagua",
        "code" : "063",
        "children" : [
          {
            "code" : "6301",
            "name" : "San Fernando",
            "latitude" : -34.5833333,
            "longitude" : -70.9666667
          },
          {
            "code" : "6302",
            "name" : "Chépica",
            "latitude" : -34.7333333,
            "longitude" : -71.2833333
          },
          {
            "code" : "6303",
            "name" : "Chimbarongo",
            "latitude" : -34.7,
            "longitude" : -71.05
          },
          {
            "code" : "6304",
            "name" : "Lolol",
            "latitude" : -34.7286111,
            "longitude" : -71.6447222
          },
          {
            "code" : "6305",
            "name" : "Nancagua",
            "latitude" : -34.6666667,
            "longitude" : -71.2166667
          },
          {
            "code" : "6306",
            "name" : "Palmilla",
            "latitude" : -34.6,
            "longitude" : -71.3666667
          },
          {
            "code" : "6307",
            "name" : "Peralillo",
            "latitude" : -34.4833333,
            "longitude" : -71.4833333
          },
          {
            "code" : "6308",
            "name" : "Placilla",
            "latitude" : -34.6333333,
            "longitude" : -71.1166667
          },
          {
            "code" : "6309",
            "name" : "Pumanque",
            "latitude" : -34.6,
            "longitude" : -71.6666667
          },
          {
            "code" : "6310",
            "name" : "Santa Cruz",
            "latitude" : -34.6333333,
            "longitude" : -71.3666667
          }
        ]
      }
    ]
  },
  {
    "code" : "07",
    "name" : "Maule",
    "children" : [
      {
        "name" : "Talca",
        "code" : "071",
        "children" : [
          {
            "code" : "7101",
            "name" : "Talca",
            "latitude" : -35.4333333,
            "longitude" : -71.6666667
          },
          {
            "code" : "7102",
            "name" : "Constitución",
            "latitude" : -35.3333333,
            "longitude" : -72.4166667
          },
          {
            "code" : "7103",
            "name" : "Curepto",
            "latitude" : -35.0833333,
            "longitude" : -72.0166667
          },
          {
            "code" : "7104",
            "name" : "Empedrado",
            "latitude" : -35.6,
            "longitude" : -72.2833333
          },
          {
            "code" : "7105",
            "name" : "Maule",
            "latitude" : -35.5333333,
            "longitude" : -71.7
          },
          {
            "code" : "7106",
            "name" : "Pelarco",
            "latitude" : -35.3833333,
            "longitude" : -71.45
          },
          {
            "code" : "7107",
            "name" : "Pencahue",
            "latitude" : -35.4,
            "longitude" : -71.8166667
          },
          {
            "code" : "7108",
            "name" : "Río Claro",
            "latitude" : -35.2833333,
            "longitude" : -71.2666667
          },
          {
            "code" : "7109",
            "name" : "San Clemente",
            "latitude" : -35.55,
            "longitude" : -71.4833333
          },
          {
            "code" : "7110",
            "name" : "San Rafael",
            "latitude" : -35.3166667,
            "longitude" : -71.5333333
          }
        ]
      },
      {
        "name" : "Cauquenes",
        "code" : "072",
        "children" : [
          {
            "code" : "7201",
            "name" : "Cauquenes",
            "latitude" : -35.9666667,
            "longitude" : -72.35
          },
          {
            "code" : "7202",
            "name" : "Chanco",
            "latitude" : -35.7333333,
            "longitude" : -72.5333333
          },
          {
            "code" : "7203",
            "name" : "Pelluhue",
            "latitude" : -35.8333333,
            "longitude" : -72.6333333
          }
        ]
      },
      {
        "name" : "Curicó",
        "code" : "073",
        "children" : [
          {
            "code" : "7301",
            "name" : "Curicó",
            "latitude" : -34.9833333,
            "longitude" : -71.2333333
          },
          {
            "code" : "7302",
            "name" : "Hualañé",
            "latitude" : -34.9766667,
            "longitude" : -71.8047222
          },
          {
            "code" : "7303",
            "name" : "Licantén",
            "latitude" : -34.9833333,
            "longitude" : -72
          },
          {
            "code" : "7304",
            "name" : "Molina",
            "latitude" : -34.1166667,
            "longitude" : -71.2833333
          },
          {
            "code" : "7305",
            "name" : "Rauco",
            "latitude" : -34.9333333,
            "longitude" : -71.3166667
          },
          {
            "code" : "7306",
            "name" : "Romeral",
            "latitude" : -34.9666667,
            "longitude" : -71.1333333
          },
          {
            "code" : "7307",
            "name" : "Sagrada Familia",
            "latitude" : -35,
            "longitude" : -71.3833333
          },
          {
            "code" : "7308",
            "name" : "Teno",
            "latitude" : -34.8666667,
            "longitude" : -71.1833333
          },
          {
            "code" : "7309",
            "name" : "Vichuquén",
            "latitude" : -34.8833333,
            "longitude" : -72
          }
        ]
      },
      {
        "name" : "Linares",
        "code" : "074",
        "children" : [
          {
            "code" : "7401",
            "name" : "Linares",
            "latitude" : -35.85,
            "longitude" : -71.6
          },
          {
            "code" : "7402",
            "name" : "Colbún",
            "latitude" : -35.7,
            "longitude" : -71.4166667
          },
          {
            "code" : "7403",
            "name" : "Longaví",
            "latitude" : -35.9666667,
            "longitude" : -71.6833333
          },
          {
            "code" : "7404",
            "name" : "Parral",
            "latitude" : -36.15,
            "longitude" : -71.8333333
          },
          {
            "code" : "7405",
            "name" : "Retiro",
            "latitude" : -36.05,
            "longitude" : -71.7666667
          },
          {
            "code" : "7406",
            "name" : "San Javier",
            "latitude" : -35.6,
            "longitude" : -71.75
          },
          {
            "code" : "7407",
            "name" : "Villa Alegre",
            "latitude" : -35.6666667,
            "longitude" : -71.75
          },
          {
            "code" : "7408",
            "name" : "Yerbas Buenas",
            "latitude" : -35.75,
            "longitude" : -71.5833333
          }
        ]
      }
    ]
  },
  {
    "code" : "08",
    "name" : "Biobío",
    "children" : [
      {
        "name" : "Ñuble",
        "code" : "084",
        "children" : [
          {
            "code" : "8401",
            "name" : "Chillán",
            "latitude" : -36.6,
            "longitude" : -72.1166667
          },
          {
            "code" : "8406",
            "name" : "Chillán Viejo",
            "latitude" : -36.6166667,
            "longitude" : -72.1333333
          },
          {
            "code" : "8413",
            "name" : "Quillón",
            "latitude" : -36.7333333,
            "longitude" : -72.4666667
          },
          {
            "code" : "8402",
            "name" : "Bulnes",
            "latitude" : -36.741987,
            "longitude" : -72.301429
          },
          {
            "code" : "8418",
            "name" : "San Ignacio",
            "latitude" : -36.8,
            "longitude" : -72.0333333
          },
          {
            "code" : "8407",
            "name" : "El Carmen",
            "latitude" : -36.899444,
            "longitude" : -72.032313
          },
          {
            "code" : "8411",
            "name" : "Pinto",
            "latitude" : -36.7,
            "longitude" : -71.9
          },
          {
            "code" : "8410",
            "name" : "Pemuco",
            "latitude" : -36.9666667,
            "longitude" : -72.1
          },
          {
            "code" : "8421",
            "name" : "Yungay",
            "latitude" : -37.1166667,
            "longitude" : -72.0166667
          },
          {
            "code" : "8414",
            "name" : "Quirihue",
            "latitude" : -36.2833333,
            "longitude" : -72.5333333
          },
          {
            "code" : "8403",
            "name" : "Cobquecura",
            "latitude" : -36.1333333,
            "longitude" : -72.7833333
          },
          {
            "code" : "8408",
            "name" : "Ninhue",
            "latitude" : -36.4,
            "longitude" : -72.4
          },
          {
            "code" : "8420",
            "name" : "Treguaco",
            "latitude" : -36.4333333,
            "longitude" : -72.6666667
          },
          {
            "code" : "8404",
            "name" : "Coelemu",
            "latitude" : -36.4833333,
            "longitude" : -72.7
          },
          {
            "code" : "8412",
            "name" : "Portezuelo",
            "latitude" : -36.5333333,
            "longitude" : -72.4333333
          },
          {
            "code" : "8415",
            "name" : "Ránquil",
            "latitude" : -36.65,
            "longitude" : -72.55
          },
          {
            "code" : "8416",
            "name" : "San Carlos",
            "latitude" : -36.4247222,
            "longitude" : -71.9580556
          },
          {
            "code" : "8409",
            "name" : "Ñiquén",
            "latitude" : -36.3,
            "longitude" : -71.9
          },
          {
            "code" : "8405",
            "name" : "Coihueco",
            "latitude" : -36.6166667,
            "longitude" : -71.8333333
          },
          {
            "code" : "8417",
            "name" : "San Fabián",
            "latitude" : -36.55,
            "longitude" : -71.55
          },
          {
            "code" : "8419",
            "name" : "San Nicolás",
            "latitude" : -36.5,
            "longitude" : -72.2166667
          }
        ]
      },
      {
        "name" : "Concepción",
        "code" : "081",
        "children" : [
          {
            "code" : "8101",
            "name" : "Concepción",
            "latitude" : -36.8333333,
            "longitude" : -73.05
          },
          {
            "code" : "8102",
            "name" : "Coronel",
            "latitude" : -37.0166667,
            "longitude" : -73.1333333
          },
          {
            "code" : "8103",
            "name" : "Chiguayante",
            "latitude" : -36.9166667,
            "longitude" : -73.0166667
          },
          {
            "code" : "8104",
            "name" : "Florida",
            "latitude" : -36.8166667,
            "longitude" : -72.6666667
          },
          {
            "code" : "8105",
            "name" : "Hualqui",
            "latitude" : -36.9666667,
            "longitude" : -72.9333333
          },
          {
            "code" : "8106",
            "name" : "Lota",
            "latitude" : -37.087073,
            "longitude" : -73.156056
          },
          {
            "code" : "8107",
            "name" : "Penco",
            "latitude" : -36.7333333,
            "longitude" : -72.9833333
          },
          {
            "code" : "8108",
            "name" : "San Pedro de la Paz",
            "latitude" : -36.8333333,
            "longitude" : -73.1166667
          },
          {
            "code" : "8109",
            "name" : "Santa Juana",
            "latitude" : -37.1666667,
            "longitude" : -72.9333333
          },
          {
            "code" : "8110",
            "name" : "Talcahuano",
            "latitude" : -36.7166667,
            "longitude" : -73.1166667
          },
          {
            "code" : "8111",
            "name" : "Tomé",
            "latitude" : -36.6166667,
            "longitude" : -72.95
          },
          {
            "code" : "8112",
            "name" : "Hualpén",
            "latitude" : -36.7833333,
            "longitude" : -73.0833333
          }
        ]
      },
      {
        "name" : "Arauco",
        "code" : "082",
        "children" : [
          {
            "code" : "8201",
            "name" : "Lebu",
            "latitude" : -37.6166667,
            "longitude" : -73.65
          },
          {
            "code" : "8202",
            "name" : "Arauco",
            "latitude" : -37.25,
            "longitude" : -73.3166667
          },
          {
            "code" : "8203",
            "name" : "Cañete",
            "latitude" : -37.8,
            "longitude" : -73.3833333
          },
          {
            "code" : "8204",
            "name" : "Contulmo",
            "latitude" : -38,
            "longitude" : -73.2333333
          },
          {
            "code" : "8205",
            "name" : "Curanilahue",
            "latitude" : -37.4666667,
            "longitude" : -73.35
          },
          {
            "code" : "8206",
            "name" : "Los Álamos",
            "latitude" : -37.6166667,
            "longitude" : -73.4666667
          },
          {
            "code" : "8207",
            "name" : "Tirúa",
            "latitude" : -38.3333333,
            "longitude" : -73.5
          }
        ]
      },
      {
        "name" : "Biobío",
        "code" : "083",
        "children" : [
          {
            "code" : "8301",
            "name" : "Los Ángeles",
            "latitude" : -37.4666667,
            "longitude" : -72.35
          },
          {
            "code" : "8302",
            "name" : "Antuco",
            "latitude" : -37.3333333,
            "longitude" : -71.6833333
          },
          {
            "code" : "8303",
            "name" : "Cabrero",
            "latitude" : -37.0333333,
            "longitude" : -72.4
          },
          {
            "code" : "8304",
            "name" : "Laja",
            "latitude" : -37.2666667,
            "longitude" : -72.7
          },
          {
            "code" : "8305",
            "name" : "Mulchén",
            "latitude" : -37.7166667,
            "longitude" : -72.2333333
          },
          {
            "code" : "8306",
            "name" : "Nacimiento",
            "latitude" : -37.5,
            "longitude" : -72.6666667
          },
          {
            "code" : "8307",
            "name" : "Negrete",
            "latitude" : -37.5833333,
            "longitude" : -72.5166667
          },
          {
            "code" : "8308",
            "name" : "Quilaco",
            "latitude" : -37.6666667,
            "longitude" : -71.9833333
          },
          {
            "code" : "8309",
            "name" : "Quilleco",
            "latitude" : -37.4666667,
            "longitude" : -71.9666667
          },
          {
            "code" : "8310",
            "name" : "San Rosendo",
            "latitude" : -37.2666667,
            "longitude" : -72.7166667
          },
          {
            "code" : "8311",
            "name" : "Santa Bárbara",
            "latitude" : -37.6666667,
            "longitude" : -72.0166667
          },
          {
            "code" : "8312",
            "name" : "Tucapel",
            "latitude" : -37.2833333,
            "longitude" : -71.95
          },
          {
            "code" : "8313",
            "name" : "Yumbel",
            "latitude" : -37.1333333,
            "longitude" : -72.5333333
          },
          {
            "code" : "8314",
            "name" : "Alto Biobío",
            "latitude" : -38.05,
            "longitude" : -71.3166667
          }
        ]
      }
    ]
  },
  {
    "code" : "09",
    "name" : "Araucanía",
    "children" : [
      {
        "name" : "Cautín",
        "code" : "091",
        "children" : [
          {
            "code" : "9101",
            "name" : "Temuco",
            "latitude" : -38.75,
            "longitude" : -72.6666667
          },
          {
            "code" : "9102",
            "name" : "Carahue",
            "latitude" : -38.7,
            "longitude" : -73.1666667
          },
          {
            "code" : "9103",
            "name" : "Cunco",
            "latitude" : -38.9166667,
            "longitude" : -72.0333333
          },
          {
            "code" : "9104",
            "name" : "Curarrehue",
            "latitude" : -39.35,
            "longitude" : -71.5833333
          },
          {
            "code" : "9105",
            "name" : "Freire",
            "latitude" : -38.95,
            "longitude" : -72.6333333
          },
          {
            "code" : "9106",
            "name" : "Galvarino",
            "latitude" : -38.4,
            "longitude" : -72.7833333
          },
          {
            "code" : "9107",
            "name" : "Gorbea",
            "latitude" : -39.1,
            "longitude" : -72.6833333
          },
          {
            "code" : "9108",
            "name" : "Lautaro",
            "latitude" : -38.5291667,
            "longitude" : -72.435
          },
          {
            "code" : "9109",
            "name" : "Loncoche",
            "latitude" : -39.3666667,
            "longitude" : -72.6333333
          },
          {
            "code" : "9110",
            "name" : "Melipeuco",
            "latitude" : -38.85,
            "longitude" : -71.7
          },
          {
            "code" : "9111",
            "name" : "Nueva Imperial",
            "latitude" : -38.7333333,
            "longitude" : -72.95
          },
          {
            "code" : "9112",
            "name" : "Padre las Casas",
            "latitude" : -38.7666667,
            "longitude" : -72.6
          },
          {
            "code" : "9113",
            "name" : "Perquenco",
            "latitude" : -38.4166667,
            "longitude" : -72.3833333
          },
          {
            "code" : "9114",
            "name" : "Pitrufquén",
            "latitude" : -38.9833333,
            "longitude" : -72.65
          },
          {
            "code" : "9115",
            "name" : "Pucón",
            "latitude" : -39.2666667,
            "longitude" : -71.9666667
          },
          {
            "code" : "9116",
            "name" : "Saavedra",
            "latitude" : -38.7833333,
            "longitude" : -73.4
          },
          {
            "code" : "9117",
            "name" : "Teodoro Schmidt",
            "latitude" : -38.9666667,
            "longitude" : -73.05
          },
          {
            "code" : "9118",
            "name" : "Toltén",
            "latitude" : -39.2166667,
            "longitude" : -73.2333333
          },
          {
            "code" : "9119",
            "name" : "Vilcún",
            "latitude" : -39.1183333,
            "longitude" : -72.3794444
          },
          {
            "code" : "9120",
            "name" : "Villarrica",
            "latitude" : -39.2666667,
            "longitude" : -72.2166667
          },
          {
            "code" : "9121",
            "name" : "Cholchol",
            "latitude" : -38.6,
            "longitude" : -72.85
          }
        ]
      },
      {
        "name" : "Malleco",
        "code" : "092",
        "children" : [
          {
            "code" : "9201",
            "name" : "Angol",
            "latitude" : -37.8,
            "longitude" : -72.7166667
          },
          {
            "code" : "9202",
            "name" : "Collipulli",
            "latitude" : -37.95,
            "longitude" : -72.4333333
          },
          {
            "code" : "9203",
            "name" : "Curacautín",
            "latitude" : -38.4333333,
            "longitude" : -71.8833333
          },
          {
            "code" : "9204",
            "name" : "Ercilla",
            "latitude" : -38.05,
            "longitude" : -72.3833333
          },
          {
            "code" : "9205",
            "name" : "Lonquimay",
            "latitude" : -38.4333333,
            "longitude" : -71.2333333
          },
          {
            "code" : "9206",
            "name" : "Los Sauces",
            "latitude" : -37.9666667,
            "longitude" : -72.8333333
          },
          {
            "code" : "9207",
            "name" : "Lumaco",
            "latitude" : -38.15,
            "longitude" : -72.9166667
          },
          {
            "code" : "9208",
            "name" : "Purén",
            "latitude" : -38.0166667,
            "longitude" : -73.0833333
          },
          {
            "code" : "9209",
            "name" : "Renaico",
            "latitude" : -37.6666667,
            "longitude" : -72.5833333
          },
          {
            "code" : "9210",
            "name" : "Traiguén",
            "latitude" : -38.25,
            "longitude" : -72.6833333
          },
          {
            "code" : "9211",
            "name" : "Victoria",
            "latitude" : -38.2166667,
            "longitude" : -72.3333333
          }
        ]
      }
    ]
  },
  {
    "code" : "14",
    "name" : "Los Ríos",
    "children" : [
      {
        "name" : "Valdivia",
        "code" : "041",
        "children" : [
          {
            "code" : "14101",
            "name" : "Valdivia",
            "latitude" : -39.8,
            "longitude" : -73.2333333
          },
          {
            "code" : "14102",
            "name" : "Corral",
            "latitude" : -39.8666667,
            "longitude" : -73.4333333
          },
          {
            "code" : "14103",
            "name" : "Lanco",
            "latitude" : -39.4333333,
            "longitude" : -72.7666667
          },
          {
            "code" : "14104",
            "name" : "Los Lagos",
            "latitude" : -39.85,
            "longitude" : -72.8333333
          },
          {
            "code" : "14105",
            "name" : "Máfil",
            "latitude" : -39.65,
            "longitude" : -72.95
          },
          {
            "code" : "14106",
            "name" : "Mariquina",
            "latitude" : -39.5166667,
            "longitude" : -72.9666667
          },
          {
            "code" : "14107",
            "name" : "Paillaco",
            "latitude" : -40.0666667,
            "longitude" : -72.8833333
          },
          {
            "code" : "14108",
            "name" : "Panguipulli",
            "latitude" : -39.6333333,
            "longitude" : -72.3333333
          }
        ]
      },
      {
        "name" : "Ranco",
        "code" : "042",
        "children" : [
          {
            "code" : "14201",
            "name" : "La Unión",
            "latitude" : -40.2833333,
            "longitude" : -73.0833333
          },
          {
            "code" : "14202",
            "name" : "Futrono",
            "latitude" : -40.1333333,
            "longitude" : -72.4
          },
          {
            "code" : "14203",
            "name" : "Lago Ranco",
            "latitude" : -40.3166667,
            "longitude" : -72.5
          },
          {
            "code" : "14204",
            "name" : "Río Bueno",
            "latitude" : -40.3166667,
            "longitude" : -72.9666667
          }
        ]
      }
    ]
  },
  {
    "code" : "10",
    "name" : "Los Lagos",
    "children" : [
      {
        "name" : "Llanquihue",
        "code" : "101",
        "children" : [
          {
            "code" : "10101",
            "name" : "Puerto Montt",
            "latitude" : -41.4666667,
            "longitude" : -72.9333333
          },
          {
            "code" : "10102",
            "name" : "Calbuco",
            "latitude" : -41.7666667,
            "longitude" : -73.1333333
          },
          {
            "code" : "10103",
            "name" : "Cochamó",
            "latitude" : -41.5,
            "longitude" : -72.3166667
          },
          {
            "code" : "10104",
            "name" : "Fresia",
            "latitude" : -41.15,
            "longitude" : -73.45
          },
          {
            "code" : "10105",
            "name" : "Frutillar",
            "latitude" : -41.1166667,
            "longitude" : -73.1
          },
          {
            "code" : "10106",
            "name" : "Los Muermos",
            "latitude" : -41.4,
            "longitude" : -73.4833333
          },
          {
            "code" : "10107",
            "name" : "Llanquihue",
            "latitude" : -41.25,
            "longitude" : -73.0166667
          },
          {
            "code" : "10108",
            "name" : "Maullín",
            "latitude" : -41.6166667,
            "longitude" : -73.6
          },
          {
            "code" : "10109",
            "name" : "Puerto Varas",
            "latitude" : -41.3166667,
            "longitude" : -72.9833333
          }
        ]
      },
      {
        "name" : "Chiloé",
        "code" : "102",
        "children" : [
          {
            "code" : "10201",
            "name" : "Castro",
            "latitude" : -42.4666667,
            "longitude" : -73.8
          },
          {
            "code" : "10202",
            "name" : "Ancud",
            "latitude" : -41.8666667,
            "longitude" : -73.8333333
          },
          {
            "code" : "10203",
            "name" : "Chonchi",
            "latitude" : -42.6166667,
            "longitude" : -73.8166667
          },
          {
            "code" : "10204",
            "name" : "Curaco de Vélez",
            "latitude" : -42.4333333,
            "longitude" : -73.5833333
          },
          {
            "code" : "10205",
            "name" : "Dalcahue",
            "latitude" : -42.3666667,
            "longitude" : -73.7
          },
          {
            "code" : "10206",
            "name" : "Puqueldón",
            "latitude" : -42.5833333,
            "longitude" : -73.6333333
          },
          {
            "code" : "10207",
            "name" : "Queilén",
            "latitude" : -42.8666667,
            "longitude" : -73.4666667
          },
          {
            "code" : "10208",
            "name" : "Quellón",
            "latitude" : -43.1,
            "longitude" : -73.6
          },
          {
            "code" : "10209",
            "name" : "Quemchi",
            "latitude" : -42.1333333,
            "longitude" : -73.5166667
          },
          {
            "code" : "10210",
            "name" : "Quinchao",
            "latitude" : -42.5333333,
            "longitude" : -73.4166667
          }
        ]
      },
      {
        "name" : "Osorno",
        "code" : "103",
        "children" : [
          {
            "code" : "10301",
            "name" : "Osorno",
            "latitude" : -40.5666667,
            "longitude" : -73.15
          },
          {
            "code" : "10302",
            "name" : "Puerto Octay",
            "latitude" : -40.9666667,
            "longitude" : -72.9
          },
          {
            "code" : "10303",
            "name" : "Purranque",
            "latitude" : -40.9166667,
            "longitude" : -73.1666667
          },
          {
            "code" : "10304",
            "name" : "Puyehue",
            "latitude" : -40.6666667,
            "longitude" : -72.6166667
          },
          {
            "code" : "10305",
            "name" : "Río Negro",
            "latitude" : -40.7833333,
            "longitude" : -73.2333333
          },
          {
            "code" : "10306",
            "name" : "San Juan de la Costa",
            "latitude" : -40.5166667,
            "longitude" : -73.4
          },
          {
            "code" : "10307",
            "name" : "San Pablo",
            "latitude" : -40.4,
            "longitude" : -73.0166667
          }
        ]
      },
      {
        "name" : "Palena",
        "code" : "104",
        "children" : [
          {
            "code" : "10401",
            "name" : "Chaitén",
            "latitude" : -42.9194444,
            "longitude" : -72.7088889
          },
          {
            "code" : "10402",
            "name" : "Futaleufú",
            "latitude" : -43.1666667,
            "longitude" : -71.85
          },
          {
            "code" : "10403",
            "name" : "Hualaihué",
            "latitude" : -42.0166667,
            "longitude" : -72.6833333
          },
          {
            "code" : "10404",
            "name" : "Palena",
            "latitude" : -43.6166667,
            "longitude" : -71.8
          }
        ]
      }
    ]
  },
  {
    "code" : "11",
    "name" : "Aysén",
    "children" : [
      {
        "name" : "Coihaique",
        "code" : "111",
        "children" : [
          {
            "code" : "11101",
            "name" : "Coyhaique",
            "latitude" : -45.5666667,
            "longitude" : -72.0666667
          },
          {
            "code" : "11102",
            "name" : "Lago Verde",
            "latitude" : -44.2333333,
            "longitude" : -71.8333333
          }
        ]
      },
      {
        "name" : "Aysén",
        "code" : "112",
        "children" : [
          {
            "code" : "11201",
            "name" : "Aysén",
            "latitude" : -45.4,
            "longitude" : -72.7
          },
          {
            "code" : "11202",
            "name" : "Cisnes",
            "latitude" : -44.75,
            "longitude" : -72.7
          },
          {
            "code" : "11203",
            "name" : "Guaitecas",
            "latitude" : -43.8833333,
            "longitude" : -73.7333333
          }
        ]
      },
      {
        "name" : "Capitán Prat",
        "code" : "113",
        "children" : [
          {
            "code" : "11301",
            "name" : "Cochrane",
            "latitude" : -47.2666667,
            "longitude" : -72.55
          },
          {
            "code" : "11302",
            "name" : "O’Higgins",
            "latitude" : -48.4666667,
            "longitude" : -72.5666667
          },
          {
            "code" : "11303",
            "name" : "Tortel",
            "latitude" : -47.8333333,
            "longitude" : -73.5666667
          }
        ]
      },
      {
        "name" : "General Carrera",
        "code" : "114",
        "children" : [
          {
            "code" : "11401",
            "name" : "Chile Chico",
            "latitude" : -46.55,
            "longitude" : -71.7333333
          },
          {
            "code" : "11402",
            "name" : "Río Ibáñez",
            "latitude" : -46.3,
            "longitude" : -71.9333333
          }
        ]
      }
    ]
  },
  {
    "code" : "12",
    "name" : "Magallanes",
    "children" : [
      {
        "name" : "Magallanes",
        "code" : "121",
        "children" : [
          {
            "code" : "12101",
            "name" : "Punta Arenas",
            "latitude" : -53.1669444,
            "longitude" : -70.9336111
          },
          {
            "code" : "12102",
            "name" : "Laguna Blanca",
            "latitude" : -52.25,
            "longitude" : -71.9166667
          },
          {
            "code" : "12103",
            "name" : "Río Verde",
            "latitude" : -52.65,
            "longitude" : -71.4833333
          },
          {
            "code" : "12104",
            "name" : "San Gregorio",
            "latitude" : -52.3166667,
            "longitude" : -69.6833333
          }
        ]
      },
      {
        "name" : "Antártica Chilena",
        "code" : "122",
        "children" : [
          {
            "code" : "12201",
            "name" : "Cabo de Hornos (Ex. Navarino)",
            "latitude" : -54.9333333,
            "longitude" : -67.6166667
          },
          {
            "code" : "12202",
            "name" : "Antártica",
            "latitude" : -75,
            "longitude" : -71.5
          }
        ]
      },
      {
        "name" : "Tierra del Fuego",
        "code" : "123",
        "children" : [
          {
            "code" : "12301",
            "name" : "Porvenir",
            "latitude" : -53.3,
            "longitude" : -70.3666667
          },
          {
            "code" : "12302",
            "name" : "Primavera",
            "latitude" : -52.7166667,
            "longitude" : -69.25
          },
          {
            "code" : "12303",
            "name" : "Timaukel",
            "latitude" : -53.6666667,
            "longitude" : -69.9
          }
        ]
      },
      {
        "name" : "Última Esperanza",
        "code" : "124",
        "children" : [
          {
            "code" : "12401",
            "name" : "Natales",
            "latitude" : -51.7333333,
            "longitude" : -72.5166667
          },
          {
            "code" : "12402",
            "name" : "Torres del Paine",
            "latitude" : -51.2666667,
            "longitude" : -72.35
          }
        ]
      }
    ]
  },
  {
    "code" : "13",
    "name" : "Metropolitana",
    "children" : [
      {
        "name" : "Santiago",
        "code" : "131",
        "children" : [
          {
            "code" : "13101",
            "name" : "Santiago",
            "latitude" : -33.45,
            "longitude" : -70.6666667
          },
          {
            "code" : "13102",
            "name" : "Cerrillos",
            "latitude" : -33.4833333,
            "longitude" : -70.7
          },
          {
            "code" : "13103",
            "name" : "Cerro Navia",
            "latitude" : -33.4166667,
            "longitude" : -70.7166667
          },
          {
            "code" : "13104",
            "name" : "Conchalí",
            "latitude" : -33.35,
            "longitude" : -70.6166667
          },
          {
            "code" : "13105",
            "name" : "El Bosque",
            "latitude" : -33.5666667,
            "longitude" : -70.7
          },
          {
            "code" : "13106",
            "name" : "Estación Central",
            "latitude" : -33.463315,
            "longitude" : -70.702976
          },
          {
            "code" : "13107",
            "name" : "Huechuraba",
            "latitude" : -33.35,
            "longitude" : -70.6666667
          },
          {
            "code" : "13108",
            "name" : "Independencia",
            "latitude" : -33.421988,
            "longitude" : -70.654932
          },
          {
            "code" : "13109",
            "name" : "La Cisterna",
            "latitude" : -33.55,
            "longitude" : -70.6833333
          },
          {
            "code" : "13110",
            "name" : "La Florida",
            "latitude" : -33.55,
            "longitude" : -70.5666667
          },
          {
            "code" : "13111",
            "name" : "La Granja",
            "latitude" : -33.5833333,
            "longitude" : -70.5833333
          },
          {
            "code" : "13112",
            "name" : "La Pintana",
            "latitude" : -33.5833333,
            "longitude" : -70.6166667
          },
          {
            "code" : "13113",
            "name" : "La Reina",
            "latitude" : -33.45,
            "longitude" : -70.55
          },
          {
            "code" : "13114",
            "name" : "Las Condes",
            "latitude" : -33.4166667,
            "longitude" : -70.5833333
          },
          {
            "code" : "13115",
            "name" : "Lo Barnechea",
            "latitude" : -33.35,
            "longitude" : -70.5166667
          },
          {
            "code" : "13116",
            "name" : "Lo Espejo",
            "latitude" : -33.5333333,
            "longitude" : -70.7166667
          },
          {
            "code" : "13117",
            "name" : "Lo Prado",
            "latitude" : -33.4333333,
            "longitude" : -70.7166667
          },
          {
            "code" : "13118",
            "name" : "Macul",
            "latitude" : -33.5,
            "longitude" : -70.5666667
          },
          {
            "code" : "13119",
            "name" : "Maipú",
            "latitude" : -33.5166667,
            "longitude" : -70.7666667
          },
          {
            "code" : "13120",
            "name" : "Ñuñoa",
            "latitude" : -33.4666667,
            "longitude" : -70.6
          },
          {
            "code" : "13121",
            "name" : "Pedro Aguirre Cerda",
            "latitude" : -33.492455,
            "longitude" : -70.678086
          },
          {
            "code" : "13122",
            "name" : "Peñalolén",
            "latitude" : -33.4833333,
            "longitude" : -70.5333333
          },
          {
            "code" : "13123",
            "name" : "Providencia",
            "latitude" : -33.4333333,
            "longitude" : -70.6166667
          },
          {
            "code" : "13124",
            "name" : "Pudahuel",
            "latitude" : -33.4333333,
            "longitude" : -70.7166667
          },
          {
            "code" : "13125",
            "name" : "Quilicura",
            "latitude" : -33.3666667,
            "longitude" : -70.75
          },
          {
            "code" : "13126",
            "name" : "Quinta Normal",
            "latitude" : -33.45,
            "longitude" : -70.7
          },
          {
            "code" : "13127",
            "name" : "Recoleta",
            "latitude" : -70.639192,
            "longitude" : -33.408148
          },
          {
            "code" : "13128",
            "name" : "Renca",
            "latitude" : -33.4,
            "longitude" : -70.7333333
          },
          {
            "code" : "13129",
            "name" : "San Joaquín",
            "latitude" : -33.5,
            "longitude" : -70.6166667
          },
          {
            "code" : "13130",
            "name" : "San Miguel",
            "latitude" : -33.5,
            "longitude" : -70.6666667
          },
          {
            "code" : "13131",
            "name" : "San Ramón",
            "latitude" : -33.45,
            "longitude" : -70.5
          },
          {
            "code" : "13132",
            "name" : "Vitacura",
            "latitude" : -33.4,
            "longitude" : -70.6
          }
        ]
      },
      {
        "name" : "Cordillera",
        "code" : "132",
        "children" : [
          {
            "code" : "13201",
            "name" : "Puente Alto",
            "latitude" : -33.6166667,
            "longitude" : -70.5833333
          },
          {
            "code" : "13202",
            "name" : "Pirque",
            "latitude" : -33.6333333,
            "longitude" : -70.55
          },
          {
            "code" : "13203",
            "name" : "San José de Maipo",
            "latitude" : -33.6333333,
            "longitude" : -70.3666667
          }
        ]
      },
      {
        "name" : "Chacabuco",
        "code" : "133",
        "children" : [
          {
            "code" : "13301",
            "name" : "Colina",
            "latitude" : -33.2,
            "longitude" : -70.6833333
          },
          {
            "code" : "13302",
            "name" : "Lampa",
            "latitude" : -33.2833333,
            "longitude" : -70.9
          },
          {
            "code" : "13303",
            "name" : "Tiltil",
            "latitude" : -33.0833333,
            "longitude" : -70.9333333
          }
        ]
      },
      {
        "name" : "Maipo",
        "code" : "134",
        "children" : [
          {
            "code" : "13401",
            "name" : "San Bernardo",
            "latitude" : -33.6,
            "longitude" : -70.7166667
          },
          {
            "code" : "13402",
            "name" : "Buin",
            "latitude" : -33.7333333,
            "longitude" : -70.75
          },
          {
            "code" : "13403",
            "name" : "Calera de Tango",
            "latitude" : -33.65,
            "longitude" : -70.8166667
          },
          {
            "code" : "13404",
            "name" : "Paine",
            "latitude" : -33.8166667,
            "longitude" : -70.75
          }
        ]
      },
      {
        "name" : "Mellipilla",
        "code" : "135",
        "children" : [
          {
            "code" : "13501",
            "name" : "Melipilla",
            "latitude" : -33.7,
            "longitude" : -71.2166667
          },
          {
            "code" : "13502",
            "name" : "Alhué",
            "latitude" : -34.04303,
            "longitude" : -71.05662
          },
          {
            "code" : "13503",
            "name" : "Curacaví",
            "latitude" : -33.4,
            "longitude" : -71.15
          },
          {
            "code" : "13504",
            "name" : "María Pinto",
            "latitude" : -33.5333333,
            "longitude" : -71.1333333
          },
          {
            "code" : "13505",
            "name" : "San Pedro",
            "latitude" : -33.9,
            "longitude" : -71.4666667
          }
        ]
      },
      {
        "name" : "Talagante",
        "code" : "136",
        "children" : [
          {
            "code" : "13601",
            "name" : "Talagante",
            "latitude" : -33.6666667,
            "longitude" : -70.9333333
          },
          {
            "code" : "13602",
            "name" : "El Monte",
            "latitude" : -33.6833333,
            "longitude" : -71.0166667
          },
          {
            "code" : "13603",
            "name" : "Isla de Maipo",
            "latitude" : -33.75,
            "longitude" : -70.9
          },
          {
            "code" : "13604",
            "name" : "Padre Hurtado",
            "latitude" : -30.2666667,
            "longitude" : -70.7
          },
          {
            "code" : "13605",
            "name" : "Peñaflor",
            "latitude" : -33.6166667,
            "longitude" : -70.9166667
          }
        ]
      }
    ]
  }
]
